CHANGES.txt
LICENSE.txt
MANIFEST.in
README.txt
setup.py
LaMark.egg-info/PKG-INFO
LaMark.egg-info/SOURCES.txt
LaMark.egg-info/dependency_links.txt
LaMark.egg-info/entry_points.txt
LaMark.egg-info/top_level.txt
lamark/__init__.py
lamark/lamark.py
lamark/lamarkargumenterror.py
lamark/lamarksyntaxerror.py
lamark/latexgen.py
lamark/lexertokens.py
lamark/lmast.py
lamark/lmlexer.py
lamark/lmparser.py
lamark/mdcodegen.py
lamark/refgen.py
lamark/runtests.py
lamark/tagparser.py
lamark/tagplugins.py
lamark/tagtokens.py
lamark/tokenstream.py
lamark/test/__init__.py
lamark/test/testlmlexer.py
lamark/test/testlmparser.py
lamark/test/testtagparser.py