Metadata-Version: 1.0
Name: LaMark
Version: 0.2.0
Summary: A tool to embedding LaTeX in Markdown
Home-page: http://github.com/beala/lamark
Author: Alex Beal
Author-email: alexlbeal@gmail.com
License: UNKNOWN
Platform: UNKNOWN
